{
	"schemaVersion": 1,
	"id": "simplify-tool-config",
	"version": "${version}",
	"name": "Simplify Tool Config",
	"description": "Mod library for simplify custom tools",
	"authors": [
		"RayvaxLux1206"
	],
	"contact": {
		"homepage": "https://fabricmc.net/",
		"sources": "https://github.com/FabricMC/fabric-example-mod"
	},
	"license": "CC0-1.0",
	"icon": "assets/simplify-tool-config/icon.png",
	"environment": "*",
	"entrypoints": {
		"main": [
			"rvl.stc_lib.SimplifyToolConfig"
		]
	},
	"mixins": [
		"simplify-tool-config.mixins.json"
	],
	"depends": {
		"fabricloader": ">=0.17.2",
		"minecraft": ">=1.20",
		"java": ">=17",
		"fabric-api": "*"
	},
	"suggests": {
		"another-mod": "*"
	}
}